{
  "description": "Kontrola po kontúzii pravej strany hrudníka - KO o 2-3 tyž",
  "type": null,
  "summary": "Thorax DX - cont - KO2t",
  "content": "<section data-x-id=\"\" data-type=\"vd\" class=\"_focus\"><aside></aside><label class=\"section-label  \">Dg.​:</label><div class=\"FieldSearch hasActions highlight truncate _focus\" data-name=\"id\" data-id=\"S20.2\" data-id-ezid=\"02089485235@12\" title=\"[S20.2] Pomlia&amp;#x17E;denie hrudn&amp;#xED;ka\" style=\"width: 50ch;\" data-ignore-visited=\"true\">[S20.2] Pomliaždenie hrudníka</div>​<label data-for=\"text\" class=\" _noval\">/​</label><div class=\"_noval Field minor\" data-name=\"text\"></div></section><section data-x-id=\"1\" data-type=\"vv\" class=\"\"><aside></aside><label class=\"section-label  \">Výkon​:</label><div class=\"FieldSearch hasActions truncate\" data-name=\"id\" data-id=\"63\" data-id-ezid=\"00000117556@14\" data-prop-body=\"200\" title=\"[63] D&amp;#xF4;kladn&amp;#xE9; vy&amp;#x161;etrenie jedn&amp;#xE9;ho org&amp;#xE1;nov&amp;#xE9;ho syst&amp;#xE9;mu alebo kontroln&amp;#xE9; vy&amp;#x161;etrenie vr&amp;#xE1;tane r&amp;#xE1;d a dokument&amp;#xE1;cie.\" style=\"width: 50ch;\">[63] Dôkladné vyšetrenie jedného orgánového systému alebo kontrolné vyšetrenie vrátane rád a dokumentácie.</div>​<label data-for=\"count\" class=\"\">počet​</label><div class=\"FieldN\" data-name=\"count\">1</div></section><section data-x-id=\"2\" data-type=\"t\" class=\"\"><aside></aside><div class=\"FieldHtml\" data-name=\"t\">S : pac. sa cíti lepšie s pretrvávajúcimi bolesťami pravej strany hrudníka v mieste udretia pri zakašlaní a náhlej zmene polohy, bolesti bez propagácie\nO : vedomie lucídne, orient., poloha aktívna, eupnoe, anikterus, acyanóza, palp. hrudník stabilný v oboch smeroch, bez krepitu, palp. alg. v mieste udretia pr. hemithoraxu miernejšia, dýchanie vezikulárne, čisté, symetrické obojstranne\nZ : stav primeraný, bez známok dušnosti, ko o 2-3 tyž., p.p. skôr\n</div></section>",
  "title": "Thorax DX - cont - KO2t",
  "shortcut": "thcdk2",
  "if": "",
  "data": {
    "_": {},
    "od": [
      {
        "id": 3,
        "order": 0,
        "props": {
          "type": "od"
        },
        "value": {
          "reason": {
            "value": "kontrola pacienta",
            "props": {
              "propValue": "K"
            }
          }
        }
      }
    ],
    "s": [
      {
        "id": 4,
        "order": 1,
        "props": {
          "type": "s"
        },
        "value": {
          "s": {
            "value": "pac. sa cíti lepšie s pretrvávajúcimi bolesťami pravej strany hrudníka v mieste udretia pri zakašlaní a náhlej zmene polohy, bolesti bez propagácie<br>",
            "props": {}
          }
        }
      }
    ],
    "o": [
      {
        "id": 5,
        "order": 2,
        "props": {
          "type": "o"
        },
        "value": {
          "o": {
            "value": "vedomie lucídne, orient., poloha aktívna, eupnoe, anikterus, acyanóza, palp. hrudník stabilný v oboch smeroch, bez krepitu, palp. alg. v mieste udretia pr. hemithoraxu miernejšia, dýchanie vezikulárne, čisté, symetrické obojstranne<br>Z: stav primeraný, bez známok dušnosti,<br>",
            "props": {}
          }
        }
      }
    ],
    "vd": [
      {
        "id": 3,
        "order": 3,
        "props": {
          "type": "vd"
        },
        "value": {
          "id": {
            "value": "[S20.2] Pomliaždenie hrudníka",
            "props": {
              "id": "S20.2",
              "idEzid": "02089485235@12"
            }
          },
          "text": {
            "value": "st.p. cont. thoracis l dx",
            "props": {}
          }
        }
      }
    ],
    "vv": [
      {
        "id": 1,
        "order": 4,
        "props": {
          "type": "vv"
        },
        "value": {
          "id": {
            "value": "[63] Dôkladné vyšetrenie jedného orgánového systému alebo kontrolné vyšetrenie vrátane rád a dokumentácie.",
            "props": {
              "propBody": 200,
              "id": 63,
              "idEzid": "00000117556@14"
            }
          },
          "count": {
            "value": "1",
            "props": {}
          }
        }
      }
    ],
    "th": [
      {
        "id": 8,
        "order": 5,
        "props": {
          "type": "th"
        },
        "value": {
          "th": {
            "value": "NSA<br>",
            "props": {}
          }
        }
      }
    ],
    "odp": [
      {
        "id": 9,
        "order": 6,
        "props": {
          "type": "odp"
        },
        "value": {
          "odp": {
            "value": "ko o 2-3 tyž., p.p. skôr<br>",
            "props": {}
          }
        }
      }
    ]
  },
  "tags": [],
  "vars": {},
  "source": "curo-open/curo-vzory#/010SALING"
}