{
  "description": "",
  "summary": "Odber krvi - delegovaný",
  "title": "Odber krvi - delegovaný",
  "shortcut": "okd",
  "if": "",
  "data": {
    "_": {},
    "vd": [
      {
        "id": 4,
        "order": 0,
        "props": {
          "type": "vd"
        },
        "value": {
          "id": {
            "value": "",
            "props": {}
          },
          "text": {
            "value": "",
            "props": {}
          }
        }
      }
    ],
    "vv": [
      {
        "id": 6,
        "order": 1,
        "props": {
          "type": "vv"
        },
        "value": {
          "id": {
            "value": "[250D] Odobratie krvi venepunkciou do jednej striekačky alebo do jednej skúmavky, vrátane odberovej súpravy, za každú súpravu.",
            "props": {
              "propType": "SVaLZ",
              "propBody": 160,
              "idClassid": "vykon",
              "idEzid": "",
              "id": "250D"
            }
          },
          "count": {
            "value": "1",
            "props": {}
          }
        }
      }
    ],
    "z-lab": [
      {
        "id": 15,
        "order": 2,
        "props": {
          "type": "z-lab"
        },
        "value": {
          "code": {
            "value": "",
            "props": {}
          },
          "comment": {
            "value": "",
            "props": {}
          },
          "recommendedBy": {
            "value": "",
            "props": {}
          },
          "labData": {
            "value": "",
            "props": {}
          }
        }
      }
    ]
  },
  "tags": [
    "sestra"
  ],
  "vars": {},
  "allowedUsers": [],
  "allowedIdentities": [],
  "owner": "admin",
  "ct": "2023-05-19T10:25:28.507Z",
  "mt": "2023-05-19T10:30:21.257Z",
  "source": "curo-open/curo-vzory#/000"
}