{
  "summary": "",
  "content": "<section data-x-id=\"11\" data-type=\"o\" class=\"\"><aside></aside><label class=\"section-label  \">Obj.​:</label><div class=\"_noval FieldHtml\" data-name=\"o\">vulva bpn., spek.:sliznice pošvy ružové, normálne pošv. prostredie, portio- epitelizované, bránka štrbina, TZ<br>palp.:pošva priestranná, čípok sakrálne, voľný, nebolestivý, uterus v AVF normálnej veľkosti, mobilný, nebolestivý, adnexálne oblasti obojstranne bez patol. rezistencie a citlivosti.<br></div></section><section data-x-id=\"15\" data-type=\"pv\" class=\"\"><aside></aside><label class=\"section-label  \">Popis vyšetrenia​:</label>​<label data-for=\"typ\" class=\" _noval\">Typ​</label><div class=\"_noval FieldList hasActions\" data-name=\"typ\" data-prop-value=\"TVS\">TVS</div>​<label data-for=\"date\" class=\" _noval\">dátum vyšetrenia​</label><div class=\"_noval FieldDate hasActions\" placeholder=\"DD.MM.RRRR\" data-name=\"date\"></div>​<label data-for=\"me\" class=\" _noval\">mnou vyžiadané​</label><div class=\"_noval FieldSwitchX hasActions\" data-name=\"me\"></div>​<label data-for=\"popis\" class=\" _noval\">popis:​</label><div class=\"_noval FieldHtml\" data-name=\"popis\">Uterus v AVF normálnej veľkosti, bez štrukturálnych zmien, endometrium , ováriá bilat. fyziol. vzhľadu a uloženia. CD bez voľnej tekutiny.<br></div></section><section data-x-id=\"4\" data-type=\"z\" class=\"\"><aside></aside><label class=\"section-label  \">Záver​:</label><div class=\"_noval FieldHtml\" data-name=\"z\">Gynekologický palp. a usg nález fyziologický.<br></div></section><section data-x-id=\"6\" data-type=\"vd\" class=\"\"><aside></aside><label class=\"section-label  \">Dg.​:</label><div class=\"_noval FieldSearch hasActions highlight truncate\" data-name=\"id\" data-ignore-visited=\"true\" title=\"[D25.9] Leiomyóm maternice, bližšie neurčený\" style=\"width: 50ch;\" data-id=\"D25.9\" data-id-ezid=\"02089373696@11\" data-id-classid=\"diagnoza\">[D25.9] Leiomyóm maternice, bližšie neurčený</div>​<label data-for=\"text\" class=\" _noval\">/​</label><div class=\"_noval Field minor\" data-name=\"text\"></div></section><section data-x-id=\"8\" data-type=\"vv\" class=\"\"><aside></aside><label class=\"section-label  \">Vykázaný výkon​:</label><div class=\"_noval FieldSearch hasActions truncate\" data-name=\"id\" data-ignore-visited=\"true\" title=\"[63] Dôkladné vyšetrenie jedného orgánového systému alebo kontrolné vyšetrenie vrátane rád a dokumentácie.\" style=\"width: 50ch;\" data-id=\"63\" data-id-ezid=\"00000117556@11\" data-id-classid=\"vykon\" data-prop-body=\"200\">[63] Dôkladné vyšetrenie jedného orgánového systému alebo kontrolné vyšetrenie vrátane rád a dokumentácie.</div>​<label data-for=\"count\" class=\"\">počet​</label><div class=\"FieldN\" data-name=\"count\">1</div></section><section data-x-id=\"9\" data-type=\"vv\" class=\"\"><aside></aside><label class=\"section-label  \">Vykázaný výkon​:</label><div class=\"_noval FieldSearch hasActions truncate\" data-name=\"id\" data-ignore-visited=\"true\" title=\"[5305] Ultrazvukové vyšetrenie intravaginálnou sondou (nemôže sa vykazovať s výkonom pod kódom 5303).\" style=\"width: 50ch;\" data-id=\"5305\" data-id-ezid=\"00000492314@11\" data-id-classid=\"vykon\" data-prop-body=\"1200\" data-prop-type=\"SVaLZ\">[5305] Ultrazvukové vyšetrenie intravaginálnou sondou (nemôže sa vykazovať s výkonom pod kódom 5303).</div>​<label data-for=\"count\" class=\"\">počet​</label><div class=\"FieldN\" data-name=\"count\">1</div></section>",
  "title": "Popôrodná kontrola",
  "shortcut": "ppk",
  "if": "",
  "data": {
    "_": {},
    "s": [
      {
        "id": 17,
        "order": 0,
        "props": {
          "type": "s"
        },
        "value": {
          "s": {
            "value": "cíti sa dobre, bolesti nemá, slabo špiní, plne kojí.<br>",
            "props": {}
          }
        }
      }
    ],
    "t": [
      {
        "id": 18,
        "order": 1,
        "props": {
          "type": "t"
        },
        "value": {
          "t": {
            "value": "<b>Pôrod:</b><br><br>",
            "props": {}
          }
        }
      }
    ],
    "o": [
      {
        "id": 11,
        "order": 2,
        "props": {
          "type": "o"
        },
        "value": {
          "o": {
            "value": "vulva bpn. epi sutura zhojená p.p. intentionem, spek.: sliznice ruožové, normál. pošvové prostredie,portio form., epitzelizované, bránka štrbina.<br>palp.: čípok sakrálne, formovaný, voľný, adnexálne oblasti obojstranne bez patologickej citlivosti a rezistencie, CD nebolestivý.<br>",
            "props": {}
          }
        }
      }
    ],
    "pv": [
      {
        "id": 15,
        "order": 3,
        "props": {
          "type": "pv"
        },
        "value": {
          "typ": {
            "value": "TVS",
            "props": {
              "propValue": "TVS"
            }
          },
          "date": {
            "value": "",
            "props": {}
          },
          "me": {
            "value": "",
            "props": {}
          },
          "popis": {
            "value": "Uterus v AVF normálnej veľkosti, bez štrukturálnych zmien, endometrium , ováriá bilat. fyziol. vzhľadu a uloženia. CD bez voľnej tekutiny.<br>",
            "props": {}
          }
        }
      }
    ],
    "z": [
      {
        "id": 4,
        "order": 4,
        "props": {
          "type": "z"
        },
        "value": {
          "z": {
            "value": "kontrolný KO.<br>Involúcia primeraná, šestonedelie fyziologické.<br>",
            "props": {}
          }
        }
      }
    ],
    "vd": [
      {
        "id": 6,
        "order": 5,
        "props": {
          "type": "vd"
        },
        "value": {
          "id": {
            "value": "[Z39.2] Ďalšie bežné sledovanie matky po pôrode",
            "props": {
              "idClassid": "diagnoza",
              "idEzid": "02089523290@11",
              "id": "Z39.2"
            }
          },
          "text": {
            "value": "",
            "props": {}
          }
        }
      }
    ],
    "vv": [
      {
        "id": 8,
        "order": 6,
        "props": {
          "type": "vv"
        },
        "value": {
          "id": {
            "value": "[2] Rady, aj cez telefon, medzi 19.oo - 08.oo hod.         (Obsah rady vid",
            "props": {
              "propBody": 200,
              "idClassid": "vykon",
              "idEzid": "02089690792@11",
              "id": 2
            }
          },
          "count": {
            "value": "1",
            "props": {}
          }
        }
      },
      {
        "id": 9,
        "order": 7,
        "props": {
          "type": "vv"
        },
        "value": {
          "id": {
            "value": "[105] Vyšetrenie a rady šestonedielke v 6. až 8. týždni po pôrode, výkon sa môže vykazovať iba raz v súvislosti so šestonedelím.",
            "props": {
              "propBody": 250,
              "idClassid": "vykon",
              "idEzid": "00000466961@11",
              "id": 105
            }
          },
          "count": {
            "value": "1",
            "props": {}
          }
        }
      }
    ]
  },
  "tags": [
    "dekurz",
    "monitory"
  ],
  "vars": {},
  "source": "curo-open/curo-vzory#/009"
}