{
  "title": "AAC l DX",
  "data": {
    "_": {},
    "t": [
      {
        "id": "",
        "order": 0,
        "props": {
          "type": "t"
        },
        "value": {
          "t": {
            "value": "S.: pac sa c&#xED;ti lep&#x161;ie, bolesti pr. AHS resp AAC miernej&#x161;ie\nO.: orient., poloha akt., eupnoe, anikter., accyanoza\nSPL : pr. AHS normokonfigurovan&#xE9;, dynamika zlep&#x161;en&#xE1;, palp. alg nad pr. AAC miernej&#x161;ie\nDop.: telesn&#xE9; &#x161;etrenie, ko o 2 ty&#x17E;.\n\n",
            "props": {}
          }
        }
      }
    ]
  },
  "source": "curo-open/curo-vzory#/saling",
  "tags": [
    "KONTROLA - TRAUMA Dg"
  ]
}