{
  "type": null,
  "summary": "VAS Th chrbtice",
  "description": "VAS Th-L chrbtice",
  "content": "<section data-x-id=\"\" data-type=\"vd\" class=\"\"><aside></aside><label class=\"section-label  \">Dg.​:</label><div class=\"FieldSearch hasActions highlight truncate\" data-name=\"id\" data-id=\"M54.6\" data-id-ezid=\"02089437251@12\" title=\"[M54.6] Boles&amp;#x165; v oblasti hrudn&amp;#xED;kovej chrbtice\" style=\"width: 50ch;\">[M54.6] Bolesť v oblasti hrudníkovej chrbtice</div>​<label data-for=\"text\" class=\" _noval\">/​</label><div class=\"_noval Field minor\" data-name=\"text\"></div></section><section data-x-id=\"1\" data-type=\"vv\" class=\"\"><aside></aside><label class=\"section-label  \">Výkon​:</label><div class=\"FieldSearch hasActions truncate\" data-name=\"id\" data-id=\"62\" data-id-ezid=\"00000117549@14\" data-prop-body=\"250\" title=\"[62] Cielen&amp;#xE9; vy&amp;#x161;etrenie dvoch alebo viacer&amp;#xFD;ch org&amp;#xE1;nov&amp;#xFD;ch syst&amp;#xE9;mov alebo dispenz&amp;#xE1;rna kontrola (cielen&amp;#xE1; anamn&amp;#xE9;za, resp. anamn&amp;#xE9;za od poslednej kontroly), popis subjekt&amp;#xED;vnych obtia&amp;#x17E;&amp;#xED;, objekt&amp;#xED;vny n&amp;#xE1;lez, vyp&amp;#xED;sanie spr&amp;#xE1;vy, z&amp;#xE1;ver, vypracovanie pl&amp;#xE1;nu do nasleduj&amp;#xFA;c\" style=\"width: 50ch;\">[62] Cielené vyšetrenie dvoch alebo viacerých orgánových systémov alebo dispenzárna kontrola (cielená anamnéza, resp. anamnéza od poslednej kontroly), popis subjektívnych obtiaží, objektívny nález, vypísanie správy, záver, vypracovanie plánu do nasledujúc</div>​<label data-for=\"count\" class=\"\">počet​</label><div class=\"FieldN\" data-name=\"count\">1</div></section><section data-x-id=\"2\" data-type=\"t\" class=\"\"><aside></aside><div class=\"FieldHtml\" data-name=\"t\">S.: pac reklamuje zhoršenie bolestí\nO.: vedomie lucídne, poloha aktíva, chôdza v norme, bez napadania\nhrudník klenutý, stabilný v oboch rovinách, dýchanie vezikulárne\nčisté, symetrické, palp. algicita ThL prechodu a Th paravertebralne s hyperon. PVS Th chrbtice s blok. postavením, dynamika ThL chrbtice obmedzená, obe SI synch. nebolestivé, kostrč palp. negat.\nRTG: bez traumat. zmien na skelete ThL chrbtice\nDg.: VAS Th chrbtice\nTh.: analgetiká, myorelaxanciá\nDop.: kľudový režim, ko o l0-14 dní, p.p. skôr\n</div></section>",
  "title": "VAS Th chrbtice",
  "if": "",
  "data": {
    "_": {},
    "od": [
      {
        "id": 12,
        "order": 0,
        "props": {
          "type": "od"
        },
        "value": {
          "reason": {
            "value": "",
            "props": {}
          }
        }
      }
    ],
    "s": [
      {
        "id": 3,
        "order": 1,
        "props": {
          "type": "s"
        },
        "value": {
          "s": {
            "value": "zhoršenie bolestí chrbta<br>",
            "props": {}
          }
        }
      }
    ],
    "o": [
      {
        "id": 4,
        "order": 2,
        "props": {
          "type": "o"
        },
        "value": {
          "o": {
            "value": "vedomie lucídne, poloha aktíva, chôdza v norme, bez napadania<br>hrudník klenutý, stabilný v oboch rovinách, dýchanie vezikulárne čisté, symetrické, palp. algicita ThL prechodu a Th paravertebralne s hyperon. PVS Th chrbtice s blok. postavením, dynamika ThL chrbtice obmedzená, obe SI synch. nebolestivé, kostrč palp. negat., <br>RTG: bez traumat. zmien na skelete ThL chrbtice<br>",
            "props": {}
          }
        }
      }
    ],
    "vd": [
      {
        "id": 2,
        "order": 3,
        "props": {
          "type": "vd"
        },
        "value": {
          "id": {
            "value": "[M54.6] Bolesť v oblasti hrudníkovej chrbtice",
            "props": {
              "idEzid": "02089437251@12",
              "id": "M54.6"
            }
          },
          "text": {
            "value": "",
            "props": {}
          }
        }
      }
    ],
    "vv": [
      {
        "id": 1,
        "order": 4,
        "props": {
          "type": "vv"
        },
        "value": {
          "id": {
            "value": "[62] Cielené vyšetrenie dvoch alebo viacerých orgánových systémov alebo dispenzárna kontrola (cielená anamnéza, resp. anamnéza od poslednej kontroly), popis subjektívnych obtiaží, objektívny nález, vypísanie správy, záver, vypracovanie plánu do nasledujúc",
            "props": {
              "propBody": 250,
              "idEzid": "00000117549@14",
              "id": 62
            }
          },
          "count": {
            "value": "1",
            "props": {}
          }
        }
      }
    ],
    "th": [
      {
        "id": 7,
        "order": 5,
        "props": {
          "type": "th"
        },
        "value": {
          "th": {
            "value": "NSA, <br>",
            "props": {}
          }
        }
      }
    ],
    "r": [
      {
        "id": 10,
        "order": 6,
        "props": {
          "type": "r"
        },
        "value": {
          "id": {
            "value": "[07226] Dexadol 25 mg gro por | gro por 10x25 mg (vre. Al/PE)",
            "props": {
              "propOl": 0,
              "propAtcName": "Dexketoprofen",
              "propSdl": 3.333,
              "propCena": 3.74,
              "propVnl": "R",
              "propUzp_1zvj": 0.114,
              "propBal": 10,
              "propGp": 1,
              "propUnit": "DF",
              "propSpUhr": "S",
              "propDpl": 3.36,
              "idClassid": "liek",
              "idEzid": "00020330205",
              "idF": "GRO POR",
              "idSp": "ora",
              "idAtc": "M01AE17",
              "idUl": "dexketoprofenum",
              "id": "07226"
            }
          },
          "schedule": {
            "value": "1-0-1-0, denne",
            "props": {
              "propWay_code": "",
              "propPeriod_t": "denne",
              "propPeriod_code": "D",
              "propParts_sleepTime": 0,
              "propParts_evening": 1,
              "propParts_noon": 0,
              "propParts_morning": 1,
              "propType": "PEV1"
            }
          },
          "qty": {
            "value": "1",
            "props": {
              "propValue": "1.00"
            }
          },
          "repeatCount": {
            "value": "",
            "props": {}
          },
          "recommendedBy": {
            "value": "",
            "props": {}
          },
          "noReplacement": {
            "value": "nie",
            "props": {
              "propValue": 0
            }
          },
          "payoff": {
            "value": "3,36",
            "props": {
              "propValue": 3.36
            }
          },
          "instruction": {
            "value": "",
            "props": {}
          },
          "reasonPayoff": {
            "value": "",
            "props": {}
          },
          "prodException": {
            "value": "nie",
            "props": {
              "propValue": 0
            }
          },
          "force": {
            "value": "nie",
            "props": {
              "propValue": 0
            }
          },
          "status": {
            "value": "0",
            "props": {}
          }
        }
      }
    ],
    "z-rtg": [
      {
        "id": 9,
        "order": 7,
        "props": {
          "type": "z-rtg"
        },
        "value": {
          "dg_text": {
            "value": "[M54.05] Panikulitída krku a chrbta v hrudníkovodriekovej oblasti",
            "props": {
              "idClassid": "diagnoza",
              "idEzid": "02089437053@12",
              "id": "M54.05"
            }
          },
          "predmet": {
            "value": "Th-L Chrbtica",
            "props": {}
          },
          "ocakavanie": {
            "value": "VAS",
            "props": {}
          },
          "epikriza": {
            "value": "",
            "props": {}
          }
        }
      }
    ],
    "odp": [
      {
        "id": 8,
        "order": 8,
        "props": {
          "type": "odp"
        },
        "value": {
          "odp": {
            "value": "analgetiká, myorelaxanciá, kľudový režim, ko o 10-14 dní, p.p. skôr<br>",
            "props": {}
          }
        }
      }
    ]
  },
  "tags": [],
  "vars": {},
  "shortcut": "vas Th",
  "source": "curo-open/curo-vzory#/010SALING"
}